akdev/__init__.py
akdev-0.1.0.dist-info/licenses/LICENSE
akdev-0.1.0.dist-info/METADATA
akdev-0.1.0.dist-info/WHEEL
akdev-0.1.0.dist-info/top_level.txt
akdev-0.1.0.dist-info/RECORD
